ultrarpc/__init__.py
ultrarpc/base.py
ultrarpc/utils.py
ultrarpc/tests/__init__.py
ultrarpc/tests/test_client.py
ultrarpc/tests/test_server.py
ultrarpc-0.5.5.dist-info/LICENSE
ultrarpc-0.5.5.dist-info/METADATA
ultrarpc-0.5.5.dist-info/WHEEL
ultrarpc-0.5.5.dist-info/top_level.txt
ultrarpc-0.5.5.dist-info/RECORD
