Metadata-Version: 2.1
Name: ultrarpc
Version: 0.5.5
Summary: Ultrarpc is 20% faster than zerorpc
Home-page: https://github.com/ikale/UltraRpc
Author: ikale
Author-email: ikale@qq.com
License: Apache-2.0
Keywords: RPC,ultrarpc
Platform: any
